k2py/__init__.py
k2py/_k2.cpython-311-darwin.so
k2py-0.2.2.dist-info/METADATA
k2py-0.2.2.dist-info/WHEEL
k2py-0.2.2.dist-info/RECORD
