Metadata-Version: 2.2
Name: k2py
Version: 0.2.2
Summary: Python bindings for k2
Keywords: k2,forced-alignment,speech,asr
Author: The LattifAI Development Team
License: Apache-2.0
Classifier: Development Status :: 4 - Beta
Classifier: Intended Audience :: Developers
Classifier: Intended Audience :: Science/Research
Classifier: License :: OSI Approved :: Apache Software License
Classifier: Programming Language :: Python :: 3
Classifier: Programming Language :: Python :: 3.10
Classifier: Programming Language :: Python :: 3.11
Classifier: Programming Language :: Python :: 3.12
Classifier: Programming Language :: Python :: 3.13
Classifier: Programming Language :: Python :: 3.14
Classifier: Programming Language :: C++
Classifier: Topic :: Scientific/Engineering :: Artificial Intelligence
Classifier: Topic :: Multimedia :: Sound/Audio :: Speech
Project-URL: Homepage, https://github.com/lattifai/k2py
Project-URL: Repository, https://github.com/lattifai/k2py.git
Project-URL: Issues, https://github.com/lattifai/k2py/issues
Requires-Python: >=3.10
